{
    "applinks": {
        "details": [
             {
               "appIDs": [ "3982L8EWZ8.TylerYust.ChoreChamp" ],
               "components": [
                 {
                    "#": "no_universal_links",
                    "exclude": true,
                    "comment": "Matches any URL whose fragment equals no_universal_links and instructs the system not to open it as a universal link"
                 },
                 {
                    "/*": "/join",
                    "comment": "Matches any URL whose path starts with /join/"
                 },
                 {
                    "/*": "/collections/*",
                    "comment": "Matches any URL whose path starts with /collections/"
                 }
               ]
             }
         ]
     },
     "webcredentials": {
        "apps": [ "3982L8EWZ8.TylerYust.ChoreChamp" ]
     },
  
      "appclips": {
          "apps": ["3982L8EWZ8.TylerYust.ChoreChamp"]
      }
}
